prickle/__init__.py
prickle/prickle.py
prickle-0.1.0.dist-info/METADATA
prickle-0.1.0.dist-info/RECORD
prickle-0.1.0.dist-info/WHEEL
prickle-0.1.0.dist-info/top_level.txt
prickle-0.1.0.dist-info/zip-safe
