Metadata-Version: 2.1
Name: prickle
Version: 0.1.0
Summary: Draw prickle plots
Home-page: https://github.com/organisation/prickle
Author: David Pattinson
Author-email: djp65@cam.ac.uk
Maintainer: David Pattinson
Maintainer-email: djp65@cam.ac.uk
License: MIT
Download-URL: https://github.com/organisation/prickle/releases/latest
Keywords: keyword0,keyword1,keyword2
Platform: Linux
Platform: MacOS
Platform: Windows
Classifier: Development Status :: 4 - Beta
Classifier: Environment :: Console
Classifier: Programming Language :: Python
